Workbook

Sheet Financial Data
A1: Financial Metric | B1: 2014 | C1: 2015 | D1: 2016
A2: Revenue (£M) | B2: 3493.9 | C2: 3950.7 | D2: 4394.9 | F2: Carillion's revenue increased by approximately 25.8% between 2014 and 2016. | G2: Company collapsed in January 2018.
A3: Profit from Operations (£M) | B3: 200.1 | C3: 209.4 | D3: 181.9 | F3: Operating profit change -9.1%: Gaining revenue but reporting less profit
A4: Net Debt (£M) | B4: 177.3 | C4: 169.8 | D4: 218.9
A5: Current Assets (£M ) | B5: 1850.1 | C5: 1813.1 | D5: 2269.8
A6: Current Liabilities (£M) | B6: 1801.9 | C6: 1771.6 | D6: 2217.4
A7: Total Assets (£M) | B7: 3890.4 | C7: 3869.5 | D7: 4433.1
A8: Operating Cash Flow (£M) | B8: 123.8 | C8: 73.3 | D8: 73.3
A10: Current Ratio | B10: =B5/B6 -> 1.0267495 | C10: =C5/C6 -> 1.0234252 | D10: =D5/D6 -> 1.0236313 | F10: The current ratio tells us whether a company has enough short-term assets to cover its short-term liabilities. | H10: Current Assets / Current Liabilities | J10: Had very little excess current assets compared with its short term obligations.
A11: Op Cash Flow / Op Profit | B11: =B8/B3 -> 0.61869065 | C11: =C8/C3 -> 0.35004776 | D11: =D8/D3 -> 0.40296866
A12: Average Net Debt (£M) | B12: 450.7 | C12: 538.9 | D12: 586.5 | F12: Average borrowing increased each year, 30.1% increase | G12: Year end borrowing lower
A13: Average Debt / Year-End Debt | B13: =B12/B4 -> 2.5420192 | C13: =C12/C4 -> 3.1737338 | D13: =D12/D4 -> 2.6793056 | H13: EBITDA = EBIT + DEPRECIATION + AMORTISATION
A15: Group Operating Profit (£m) | B15: 175 | C15: 183.4 | D15: 145.6
A16: Depreciation & Amortisation (£m) | B16: 44.8 | C16: 45.4 | D16: 45 | F16: Revenue increased, but profitability weakened.
A17: Group EBITDA (£m) (calculated) | B17: =B15+B16 -> 219.8 | C17: =C15+C16 -> 228.8 | D17: =D15+D16 -> 190.6 | F17: Operating cash flow deteriorated.
A18: Net Debt / EBITDA | B18: =B4/B17 -> 0.8066424 | C18: =C4/C17 -> 0.74213287 | D18: =D4/D17 -> 1.1484785 | F18: Average borrowing was significantly higher than year-end debt.
A20: Financial Expense (£m) | B20: 46.3 | C20: 60.3 | D20: 60.4
A21: Interest Cover (×) | B21: =B15/B20 -> 3.7796976 | C21: =C15/C20 -> 3.0414594 | D21: =D15/D20 -> 2.410596
A23: Operating Profit Margin | B23: =B3/B2 -> 0.057271244 | C23: =C3/C2 -> 0.053003265 | D23: =D3/D2 -> 0.041388883 | F23: Operating Profit Margin: Declined from 5.73% in 2014 to 4.14% in 2016, indicating that Carillion was generating less operating profit for every pound of revenue despite increasing sales.
A24: Operating Return on Assets | B24: =B3/B7 -> 0.0514343 | C24: =C3/C7 -> 0.054115519 | D24: =D3/D7 -> 0.041032235 | F24: Operating Return on Assets: Declined from 5.14% in 2014 to 4.10% in 2016, suggesting weakening profitability relative to the company's growing asset base.

Sheet Altman Z-Score
A1: Financial Metric | B1: 2014 | C1: 2015 | D1: 2016 | F1: Carillion was a construction and services company, not a traditional manufacturer.
A2: Current Assets (£M ) | B2: ='Financial Data'!B5 -> 1850.1 | C2: ='Financial Data'!C5 -> 1813.1 | D2: ='Financial Data'!D5 -> 2269.8 | F2: The original Z-score was designed for publicly traded manufacturing companies, so its thresholds may not be reliable for Carillion.
A3: Current Liabilities (£M) | B3: ='Financial Data'!B6 -> 1801.9 | C3: ='Financial Data'!C6 -> 1771.6 | D3: ='Financial Data'!D6 -> 2217.4
A4: Working Capital (£m) | B4: =B2-B3 -> 48.2 | C4: =C2-C3 -> 41.5 | D4: =D2-D3 -> 52.4
A5: Total Assets (£m) | B5: 3890.4 | C5: 3869.5 | D5: 4433.1
A6: X1: Working Capital / Total Assets | B6: =B4/B5 -> 0.012389472 | C6: =C4/C5 -> 0.0107249 | D6: =D4/D5 -> 0.011820171 | F6: Carillion's working capital was positive, but represented only about 1% of total assets throughout the three years.
A8: Retained Earnings (£m) | B8: 279.7 | C8: 410.3 | D8: 92.7
A9: X2: Retained Earnings / Total Assets | B9: =B8/B5 -> 0.071894921 | C9: =C8/C5 -> 0.10603437 | D9: =D8/D5 -> 0.020910875 | F9: Carillion's retained earnings relative to total assets increased between 2014 and 2015, before falling sharply in 2016.
A11: EBIT (£m) | B11: 200.1 | C11: 209.4 | D11: 181.9 | F11: Declined from 0.0514 in 2014 to 0.0410 in 2016, indicating that Carillion generated less operating profit relative to its total asset base. This contributed negatively to its financial distress score.
A12: X3: EBIT / Total Assets | B12: =B11/B5 -> 0.0514343 | C12: =C11/C5 -> 0.054115519 | D12: =D11/D5 -> 0.041032235
A14: Total Equity (£m) | B14: 894.5 | C14: 1016.6 | D14: 729.9
A15: Total Liabilities (£m) | B15: 2995.9 | C15: 2852.9 | D15: 3703.2
A16: X4: Equity / Total Liabilities | B16: =B14/B15 -> 0.29857472 | C16: =C14/C15 -> 0.35633916 | D16: =D14/D15 -> 0.19709981
F17: Carillion's Altman Z''-Score increased slightly from 0.97 in 2014 to 1.15 in 2015, before falling sharply to 0.63 in 2016.
A18: Altman Z''-Score | B18: =6.56*B6+3.26*B9+6.72*B12+1.05*B16 -> 0.97479432 | C18: =6.56*C6+3.26*C9+6.72*C12+1.05*C16 -> 1.1538398 | D18: =6.56*D6+3.26*D9+6.72*D12+1.05*D16 -> 0.62840119 | F18: This indicates significant financial distress, with the deterioration in 2016 suggesting an increasing risk of bankruptcy ahead of the company's collapse in January 2018.
F19: The 2015 score briefly entered the grey zone (1.10–2.60), while 2014 and 2016 were in the distress zone (below 1.10).
K32: Retained earnings are the accumulated profits a company has kept in the business over time, after accounting for dividends and other adjustments.
K33: EBIT stands for Earnings Before Interest and Taxes.

Sheet Financial Analysis and Conclusi
A1: Financial Analysis and Conclusion
A3: Carillion's financial performance between 2014 and 2016 showed several warning signs of increasing financial distress.
A5: Profitability:
A6: Despite revenue increasing by approximately 25.8%, profit from operations declined by 9.1%, suggesting that revenue growth was not translating into stronger profitability.
A7: Liquidity:
A8: The current ratio remained close to 1.0 throughout the period, indicating that Carillion maintained only a small surplus of current assets over current liabilities.
A9: Cash Flow:
A10: Operating cash flow declined from £123.8 million in 2014 to £73.3 million in 2016, indicating weakening cash generation.
A11: Debt:
A12: Average net borrowing increased from £450.7 million in 2014 to £586.5 million in 2016, suggesting growing financial pressure.
A13: Altman Z''-Score:
A14: The score increased from 0.97 in 2014 to 1.15 in 2015, before declining sharply to 0.63 in 2016. This suggests that Carillion's financial position deteriorated significantly in the years preceding its collapse.
... A17: financial vulnerability. Although the model cannot predict bankruptcy with certainty, the analysis demonstrates how financial ratios can help identify potential corporate distress.

Sheet Glossary
A1: Financial glossary
A3: Term | B3: Simple definition
A4: Revenue | B4: The total income a company earns from selling goods or providing services, before deducting expenses.
A5: Operating Profit | B5: The profit a company makes from its business operations after deducting operating expenses, but generally before interest and tax.
A6: Net Profit | B6: The profit remaining after all expenses, including interest and taxes, have been deducted. Also called profit after tax.
A7: Operating Cash Flow | B7: The actual cash generated or used by a company's normal business activities during a period.
A8: Net Debt | B8: The company's borrowings minus its cash and cash equivalents, subject to its reported definition.
A9: Current Assets | B9: Assets expected to be converted into cash, sold or used within approximately one year, such as inventory and customer payments due.
A10: Current Liabilities | B10: Debts and financial obligations generally due within one year, such as supplier payments and short-term loans.
A11: Total Assets | B11: The total value of everything the company owns or controls that is recognised as an asset.
A12: Total Liabilities | B12: All the company's financial obligations, including loans, unpaid bills and other liabilities.
A13: EBITDA | B13: Earnings Before Interest, Taxes, Depreciation and Amortisation. A measure of operating earnings before certain expenses.
A14: Interest Expense | B14: The cost a company incurs from borrowing money, such as interest on loans. | C14: EBIT / Interest Expense
A15: Current Ratio | B15: Current assets divided by current liabilities. Measures the company's ability to cover short-term obligations. | C15: Current Assets / Current Liabilities
A16: Net Debt / EBITDA | B16: Measures how large a company's net debt is relative to its annual EBITDA. | C16: Net Debt / EBITDA
A17: Interest Cover | B17: Measures how comfortably a company's earnings can cover its interest expenses.
A18: Cash Conversion Ratio | B18: Compares operating cash flow with reported profit to assess how effectively accounting profits translate into cash.
A19: Working Capital | B19: Current assets minus current liabilities. Indicates the company's short-term financial position. | C19: Current Assets − Current Liabilities
A20: Retained Earnings | B20: Accumulated profits kept in the business after dividends and other relevant accounting adjustments.
A21: Altman Z-Score | B21: The Altman Z-score is a financial model developed by Edward Altman in 1968 to estimate a company's risk of financial distress.
A22: Depreciation | B22: The systematic allocation of a physical asset's cost over its useful life.
A23: Amortisation | B23: The systematic allocation of an intangible asset's cost over its useful life.
A24: ROA (Return on Assets) | B24: Measures how efficiently a company uses its assets to generate profit.
